MANIFEST.in
README.txt
setup.py
src/NeuroUnits.egg-info/PKG-INFO
src/NeuroUnits.egg-info/SOURCES.txt
src/NeuroUnits.egg-info/dependency_links.txt
src/NeuroUnits.egg-info/entry_points.txt
src/NeuroUnits.egg-info/requires.txt
src/NeuroUnits.egg-info/top_level.txt
src/neurounits/__init__.py
src/neurounits/librarymanager.py
src/neurounits/locations.py
src/neurounits/misc.py
src/neurounits/neurounitparser.py
src/neurounits/nulogging.py
src/neurounits/nuts_io.py
src/neurounits/unit_errors.py
src/neurounits/units_misc.py
src/neurounits/ast/__init__.py
src/neurounits/ast/astobjects.py
src/neurounits/ast/astobjects_nineml.py
src/neurounits/ast/astobjects_randomvariables.py
src/neurounits/ast/base.py
src/neurounits/ast/compoundports.py
src/neurounits/ast/eqnset.py
src/neurounits/ast_annotations/__init__.py
src/neurounits/ast_annotations/bases.py
src/neurounits/ast_annotations/common.py
src/neurounits/ast_annotations/node_fixedpointannotator.py
src/neurounits/ast_annotations/node_range_byoptimiser.py
src/neurounits/ast_annotations/node_rangeexpander.py
src/neurounits/ast_annotations/node_tagger.py
src/neurounits/ast_annotations/node_toint.py
src/neurounits/ast_builder/__init__.py
src/neurounits/ast_builder/builder_visitor_propogate_dimensions.py
src/neurounits/ast_builder/builder_visitor_remove_proxies.py
src/neurounits/ast_builder/eqnsetbuilder.py
src/neurounits/ast_builder/eqnsetbuilder_symbol_proxy.py
src/neurounits/ast_builder/io_types.py
src/neurounits/ast_builder/eqnsetbuilder_io/__init__.py
src/neurounits/ast_builder/eqnsetbuilder_io/io_str_parser.py
src/neurounits/ast_operations/__init__.py
src/neurounits/ast_operations/merge_components.py
src/neurounits/codegen/__init__.py
src/neurounits/codegen/cffi_functor/__init__.py
src/neurounits/codegen/cpp/__init__.py
src/neurounits/codegen/cpp/fixed_point/__init__.py
src/neurounits/codegen/cpp/fixed_point/fixed_point_common.py
src/neurounits/codegen/cpp/fixed_point/fixed_point_network_writer.py
src/neurounits/codegen/nmodl/__init__.py
src/neurounits/codegen/nmodl/neuron_constants.py
src/neurounits/codegen/nmodl/section_writers.py
src/neurounits/codegen/population_infrastructure/__init__.py
src/neurounits/codegen/python_functor/__init__.py
