Metadata-Version: 1.1
Name: NeuroUnits
Version: 0.1.2
Summary: A library for parsing quantities and sets of equations involving units for computational neuroscience.
Home-page: https://github.com/mikehulluk/NeuroUnits
Author: Mike Hull
Author-email: mikehulluk@gmail.com
License: BSD
Platform: UNKNOWN
Classifier: Development Status :: 3 - Alpha
Classifier: Topic :: Utilities
Classifier: License :: OSI Approved :: BSD License
